dissident/__init__.py
dissident/filtering.py
dissident-0.1.0.dist-info/LICENSE
dissident-0.1.0.dist-info/METADATA
dissident-0.1.0.dist-info/WHEEL
dissident-0.1.0.dist-info/RECORD
