Metadata-Version: 2.1
Name: dissident
Version: 0.1.0
Summary: 
Author: barguzin
Author-email: noi@ucsb.edu
Requires-Python: ==3.9.17
Classifier: Programming Language :: Python :: 3
Requires-Dist: bottleneck (>=1.3.7,<2.0.0)
Requires-Dist: certifi (>=2023.7.22,<2024.0.0)
Requires-Dist: contextily (>=1.3.0,<2.0.0)
Requires-Dist: dask (>=2023.8.1,<2024.0.0)
Requires-Dist: geopandas (>=0.13.2,<0.14.0)
Requires-Dist: mercantile (>=1.2.1,<2.0.0)
Requires-Dist: netcdf4 (>=1.6.4,<2.0.0)
Requires-Dist: osmnx (>=1.6.0,<2.0.0)
Requires-Dist: xarray (>=2023.8.0,<2024.0.0)
